codespeed/__init__.py
codespeed/admin.py
codespeed/feeds.py
codespeed/models.py
codespeed/results.py
codespeed/settings.py
codespeed/urls.py
codespeed/views.py
codespeed/views_data.py
codespeed/commits/__init__.py
codespeed/commits/exceptions.py
codespeed/commits/git.py
codespeed/commits/github.py
codespeed/commits/logs.py
codespeed/commits/mercurial.py
codespeed/commits/subversion.py
codespeed/fixtures/timeline_tests.json
codespeed/migrations/0001_initial.py
codespeed/migrations/0002_median.py
codespeed/migrations/__init__.py
codespeed/south_migrations/0001_initial.py
codespeed/south_migrations/0002_auto__chg_field_report_summary.py
codespeed/south_migrations/0003_auto__add_field_revision_branch.py
codespeed/south_migrations/0004_auto__add_branch.py
codespeed/south_migrations/0005_auto__del_unique_revision_commitid_project__add_unique_revision_commit.py
codespeed/south_migrations/0006_auto__chg_field_revision_branch.py
codespeed/south_migrations/0007_auto__del_unique_revision_commitid_project_branch__add_unique_revision.py
codespeed/south_migrations/0008_auto__chg_field_benchmark_description.py
codespeed/south_migrations/0009_auto__chg_field_revision_project.py
codespeed/south_migrations/0010_auto__add_field_benchmark_default_on_comparison.py
codespeed/south_migrations/0011_auto__add_field_project_commit_browsing_url.py
codespeed/south_migrations/0011_auto__del_unique_executable_name__add_unique_executable_project_name.py
codespeed/south_migrations/0012_auto__add_field_benchmark_parent__add_field_project_commit_browsing_ur.py
codespeed/south_migrations/0013_auto__chg_field_revision_author__chg_field_environment_kernel__chg_fie.py
codespeed/south_migrations/__init__.py
codespeed/south_migrations/migrations/0001_initial.py
codespeed/south_migrations/migrations/0002_auto__chg_field_report_summary.py
codespeed/south_migrations/migrations/0003_auto__add_field_revision_branch.py
codespeed-0.11.0.dist-info/DESCRIPTION.rst
codespeed-0.11.0.dist-info/METADATA
codespeed-0.11.0.dist-info/RECORD
codespeed-0.11.0.dist-info/WHEEL
codespeed-0.11.0.dist-info/metadata.json
codespeed-0.11.0.dist-info/top_level.txt
