Metadata-Version: 2.0
Name: codespeed
Version: 0.11.0
Summary: A web application to monitor and analyze the performance of your code
Home-page: https://github.com/tobami/codespeed
Author: Miquel Torres
Author-email: tobami@gmail.com
License: GNU Lesser General Public License version 2.1
Download-URL: https://github.com/tobami/codespeed/tags
Keywords: benchmarking,visualization
Platform: UNKNOWN
Classifier: Environment :: Web Environment
Classifier: Framework :: Django
Classifier: Intended Audience :: Developers
Classifier: License :: OSI Approved :: GNU Lesser General Public License v2 (LGPLv2)
Classifier: Operating System :: OS Independent
Classifier: Programming Language :: Python
Classifier: Programming Language :: Python :: 2
Classifier: Programming Language :: Python :: 2.7
Classifier: Programming Language :: Python :: 3
Classifier: Programming Language :: Python :: 3.4
Classifier: Programming Language :: Python :: 3.5
Classifier: Topic :: Internet :: WWW/HTTP :: WSGI :: Application
Requires-Dist: django (>=1.6,<1.9)
Requires-Dist: isodate (>=0.4.7,<0.6)
